odoo8_addon_pos_restricted_customer_list-8.0.0.1.0-py2.7-nspkg.pth
odoo8_addon_pos_restricted_customer_list-8.0.0.1.0.dist-info/DESCRIPTION.rst
odoo8_addon_pos_restricted_customer_list-8.0.0.1.0.dist-info/METADATA
odoo8_addon_pos_restricted_customer_list-8.0.0.1.0.dist-info/RECORD
odoo8_addon_pos_restricted_customer_list-8.0.0.1.0.dist-info/WHEEL
odoo8_addon_pos_restricted_customer_list-8.0.0.1.0.dist-info/metadata.json
odoo8_addon_pos_restricted_customer_list-8.0.0.1.0.dist-info/namespace_packages.txt
odoo8_addon_pos_restricted_customer_list-8.0.0.1.0.dist-info/top_level.txt
odoo_addons/pos_restricted_customer_list/README.rst
odoo_addons/pos_restricted_customer_list/__init__.py
odoo_addons/pos_restricted_customer_list/__openerp__.py
odoo_addons/pos_restricted_customer_list/models/__init__.py
odoo_addons/pos_restricted_customer_list/models/res_partner.py
odoo_addons/pos_restricted_customer_list/static/src/js/pos_restricted_customer_list.js
odoo_addons/pos_restricted_customer_list/views/assets_backend.xml
odoo_addons/pos_restricted_customer_list/views/res_partner.xml
